biox/__init__.py
biox/ble/__init__.py
biox/ble/constants.py
biox/ble/device.py
biox/ble/scanner.py
biox/collector/__init__.py
biox/collector/collector.py
biox/command/__init__.py
biox/command/command.py
biox/data/__init__.py
biox/data/decode.py
biox/data/eeg_config.py
biox/data/pkg_data.py
biox/data/process.py
biox/data/signal_config.py
biox/data/dll/__init__.py
biox/data/dll/pkg_decode.dll
biox/data/dll/signal_process.dll
biox/util/__init__.py
biox/util/constants.py
biox/util/exceptions.py
biox/visualization/__init__.py
biox/visualization/realtime_plotter.py
samples/__init__.py
samples/eeg_processing_and_plot_test.py
samples/eeg_processing_no_plot_test.py
samples/eeg_with_battery_monitor.py
samples/query_device_test.py
samples/sample1.py
samples/sample3.py
samples/sample4.py
samples/sample5.py
samples/sample6.py
biox_sdk-0.4.0.dist-info/METADATA
biox_sdk-0.4.0.dist-info/WHEEL
biox_sdk-0.4.0.dist-info/top_level.txt
biox_sdk-0.4.0.dist-info/RECORD
