Metadata-Version: 2.1
Name: biox-sdk
Version: 0.4.0
Summary: a sdk for connecting with a Biox device
Author: qiucheng.su
Author-email: suqiucheng@zju.edu.cn
Keywords: bluetooth,ble,sdk
Requires-Python: >=3.7
Requires-Dist: bleak >=0.19.0
